rocket/__init__.py
rocket/rocket.py
ismail_rocket_aissaoui_group_3_aisd-1.0.0.dist-info/LICENSE.txt
ismail_rocket_aissaoui_group_3_aisd-1.0.0.dist-info/METADATA
ismail_rocket_aissaoui_group_3_aisd-1.0.0.dist-info/WHEEL
ismail_rocket_aissaoui_group_3_aisd-1.0.0.dist-info/top_level.txt
ismail_rocket_aissaoui_group_3_aisd-1.0.0.dist-info/RECORD
