Metadata-Version: 2.1
Name: ismail-rocket-aissaoui-group-3-aisd
Version: 1.0.0
Summary: An awesome package that does something
Home-page: http://pypi.python.org/pypi/irocket/
Author: ismail
Author-email: i.aissaoui@esi-sba.dz
License: LICENSE.txt
License-File: LICENSE.txt
Requires-Dist: ismail-rocket-aissaoui-group-3-aisd
